magicprompt/__init__.py
magicprompt/config.py
magicprompt/main.py
magicprompt/utils.py
test/__init__.py
test/test_prompt.py
test/test_utils.py
magicprompt-0.2.5.dist-info/METADATA
magicprompt-0.2.5.dist-info/WHEEL
magicprompt-0.2.5.dist-info/top_level.txt
magicprompt-0.2.5.dist-info/RECORD
