Metadata-Version: 2.2
Name: magicprompt
Version: 0.2.5
Summary: A powerful one line solution for collecting CLI user input with absolutely zero boilerplate
Home-page: https://gitlab.com/austinmpask/pymagicprompt
Dynamic: description
Dynamic: description-content-type
Dynamic: home-page
Dynamic: summary
